{
  "culture": "pt-BR",
  "texts": {
    "Actions": "Ações",
    "AndUnderstandThatICanUnsubscribeAtAnyTime": "e entendo que posso cancelar a inscrição a qualquer momento.",
    "BlogDeletionConfirmationMessage": "O blog '{0}' será excluído. Tem certeza?",
    "BlogFeatureNotAvailable": "Este recurso não está disponível agora. Ative com 'GlobalFeatureManager' para usá-lo.",
    "BlogId": "Blog",
    "BlogPostDeletionConfirmationMessage": "A postagem do blog '{0}' será excluída. Tem certeza?",
    "BlogPosts": "Postagem",
    "Blogs": "Blogs",
    "ChoosePreference": "Escolha a preferência...",
    "Cms": "CMS",
    "CmsKit.Comments": "Comentários",
    "CmsKit.Ratings": "Avaliações",
    "CmsKit.Reactions": "Reações",
    "CmsKit.Tags": "Tags",
    "CommentDeletionConfirmationMessage": "Este comentário e todas as respostas serão excluídos!",
    "Comments": "Comentários",
    "ContactSuccess": "Sua mensagem foi enviada com sucesso.",
    "ContentDeletionConfirmationMessage": "Tem certeza que deseja deletar este conteúdo?",
    "Contents": "Comentários",
    "CoverImage": "Imagem de capa",
    "CreateBlogPostPage": "Nova postagem",
    "CreationTime": "Hora da criação",
    "Detail": "Detalhe",
    "Details": "Detalhes",
    "DoYouPreferAdditionalEmails": "Você prefere e-mails adicionais?",
    "Edit": "Editar",
    "EmailAddress": "Endereço de e-mail",
    "EmailAddressPermissionManagement": "Com o endereço de e-mail \"{0}\", você concede as seguintes permissões.",
    "EmailToException": "Você precisa especificar o endereço de e-mail para o qual o e-mail será enviado.",
    "EndDate": "Data final",
    "EntityId": "Id da Entidade",
    "EntityType": "Tipo da entidade",
    "ExportCSV": "Exportar CSV",
    "Features": "Recursos",
    "GenericDeletionConfirmationMessage": "Tem certeza que deseja excluir '{0}'?",
    "GetDealsAndSpecialOffersForThe": "Obtenha promoções e ofertas especiais para o \"{0}\"",
    "HowMayWeHelpYou": "Como podemos ajudá-lo?",
    "IHaveReadThe": "Eu li o",
    "Message": "Mensagem",
    "Name": "Nome",
    "New": "Novo",
    "NewsletterDeleteSubscriptionMessage": "Não enviaremos mais e-mails automatizados para seus e-mails - \"{0}\".",
    "NewsletterDeleteSubscriptionSubject": "Assinatura cancelada.",
    "NewsletterDeleteSubscriptionTitle": "Seu pedido foi recebido.",
    "NewsletterEmailFooterCreateTemplateMessage": "Suas preferências de e-mail foram criadas com sucesso.",
    "NewsletterEmailFooterTemplateManageEmail": "Você pode gerenciar suas preferências de e-mail.",
    "NewsletterEmailFooterTemplateTitle": "Recebeu este e-mail porque subscreveu a nossa newsletter.",
    "NewsletterEmailFooterUpdateTemplateMessage": "Suas preferências de e-mail foram atualizadas com sucesso.",
    "NewsletterEmailMessage": "Estamos felizes por você ter nos escolhido.",
    "NewsletterEmailSubject": "Inscrito na newsletter",
    "NewsletterEmailTitle": "Obrigado por se inscrever!",
    "NewsletterEmailUnsubscriptionMessage": "Você foi removido com sucesso desta lista de assinantes e não receberá mais nenhum e-mail nosso.",
    "Newsletters": "Newsletters",
    "NewsletterSuccessMessage": "Obrigado por assinar o newsletter!",
    "NewsletterUpdatePreferenceMessage": "Suas alterações de preferência foram feitas com sucesso.",
    "NewsletterUpdatePreferenceTitle": "Preferências de e-mail",
    "NewsletterUpdatePreferenceTitleSubject": "Atualizada suas preferências de assinatura",
    "OK": "OK",
    "PageDeletionConfirmationMessage": "Tem certeza que deseja deletar esta página?",
    "PageSlugInformation": "Slug é usado no url. Seu url será '/pages/{{slug}}'.",
    "Permission:BlogManagement": "Gerenciamento de Blog",
    "Permission:BlogManagement.Create": "Criar",
    "Permission:BlogManagement.Delete": "Deletar",
    "Permission:BlogManagement.Update": "Atualizar",
    "Permission:BlogPostManagement": "Gerenciamento de postagem no blog",
    "Permission:BlogPostManagement.Create": "Criar",
    "Permission:BlogPostManagement.Delete": "Deletar",
    "Permission:BlogPostManagement.Update": "Atualizar",
    "Permission:NewsletterManagement": "Gerenciamento de newsletter",
    "Preference": "Preferência",
    "PrivacyPolicy": "Política de Privacidade",
    "RepliesToThisComment": "Respostas a este comentário",
    "ReplyTo": "Responder a",
    "SamplePageMessage": "Uma página de amostra para o módulo Pro",
    "SaveChanges": "Salvar alterações",
    "SelectAll": "Selecionar tudo",
    "SendMessage": "Enviar mensagem",
    "ShortDescription": "Descrição resumida",
    "Slug": "Slug",
    "Source": "Fonte",
    "SourceUrl": "URL da fonte",
    "StartDate": "Data inicial",
    "Subject": "Assunto",
    "SubjectPlaceholder": "Por favor digite um assunto",
    "Submit": "Enviar",
    "Subscribe": "Assinar",
    "SuccessfullyDeleted": "Excluído com sucesso!",
    "SuccessfullySaved": "Salvo com sucesso!",
    "Text": "Texto",
    "ThankYou": "Obrigado",
    "Title": "Título",
    "UpdatePreferenceSuccessMessage": "Suas preferências foram salvas.",
    "UpdateYourEmailPreferences": "Atualize suas preferências de e-mail",
    "UploadFailedMessage": "Falha no upload.",
    "UserId": "ID do usuário",
    "Username": "Nome do usuário",
    "YourEmailAddress": "Seu endereço de email",
    "YourFullName": "Seu nome completo",
    "YourMessage": "Sua mensagem",
    "Settings:Menu:CmsKit": "CMS",
    "ReceiverEmailAddress": "Endereço de Email do Destinatário",
    "CmsKitPro:Contact": "Contato"
  }
}
